odoo8_addon_redmine_import_time_entry-8.0.1.0.0.99.dev9-py2.7-nspkg.pth
odoo8_addon_redmine_import_time_entry-8.0.1.0.0.99.dev9.dist-info/METADATA
odoo8_addon_redmine_import_time_entry-8.0.1.0.0.99.dev9.dist-info/RECORD
odoo8_addon_redmine_import_time_entry-8.0.1.0.0.99.dev9.dist-info/WHEEL
odoo8_addon_redmine_import_time_entry-8.0.1.0.0.99.dev9.dist-info/namespace_packages.txt
odoo8_addon_redmine_import_time_entry-8.0.1.0.0.99.dev9.dist-info/top_level.txt
odoo_addons/redmine_import_time_entry/README.rst
odoo_addons/redmine_import_time_entry/__init__.py
odoo_addons/redmine_import_time_entry/__openerp__.py
odoo_addons/redmine_import_time_entry/data/ir_cron_data.xml
odoo_addons/redmine_import_time_entry/i18n/en.po
odoo_addons/redmine_import_time_entry/i18n/fr.po
odoo_addons/redmine_import_time_entry/models/__init__.py
odoo_addons/redmine_import_time_entry/models/account_analytic_account.py
odoo_addons/redmine_import_time_entry/models/hr_analytic_timesheet.py
odoo_addons/redmine_import_time_entry/models/hr_timesheet_sheet.py
odoo_addons/redmine_import_time_entry/models/redmine_backend.py
odoo_addons/redmine_import_time_entry/static/description/icon.png
odoo_addons/redmine_import_time_entry/static/src/img/icon.png
odoo_addons/redmine_import_time_entry/static/src/img/icon.svg
odoo_addons/redmine_import_time_entry/static/src/js/timesheet.js
odoo_addons/redmine_import_time_entry/tests/__init__.py
odoo_addons/redmine_import_time_entry/tests/test_import_time_entries.py
odoo_addons/redmine_import_time_entry/unit/__init__.py
odoo_addons/redmine_import_time_entry/unit/backend_adapter.py
odoo_addons/redmine_import_time_entry/unit/import_synchronizer.py
odoo_addons/redmine_import_time_entry/unit/mapper.py
odoo_addons/redmine_import_time_entry/views/hr_timesheet_sheet_view.xml
odoo_addons/redmine_import_time_entry/views/redmine_backend_view.xml
