Metadata-Version: 2.1
Name: odoo8-addon-redmine-import-time-entry
Version: 8.0.1.0.0.99.dev9
Summary: Redmine Import Time Entry
Home-page: http://odoo-community.org
Author: Savoir-faire Linux,Odoo Community Association (OCA)
Author-email: support@odoo-community.org
License: AGPL-3
Platform: UNKNOWN
Classifier: Programming Language :: Python
Classifier: Framework :: Odoo
Classifier: License :: OSI Approved :: GNU Affero General Public License v3
Requires-Python: ~=2.7
Requires-Dist: odoo8-addon-connector-redmine
Requires-Dist: odoo (<9.0a,>=8.0a)
